google_cloud_functions_tools/__init__.py
google_cloud_functions_tools/cors.py
google_cloud_functions_tools/firebase_verify_id.py
google_cloud_functions_tools-0.2.1.dist-info/LICENCE
google_cloud_functions_tools-0.2.1.dist-info/METADATA
google_cloud_functions_tools-0.2.1.dist-info/WHEEL
google_cloud_functions_tools-0.2.1.dist-info/top_level.txt
google_cloud_functions_tools-0.2.1.dist-info/RECORD
