Metadata-Version: 2.1
Name: google-cloud-functions-tools
Version: 0.2.1
Summary: A set of utility tools (planned mostly to be decorators) for Google Cloud Functions
Author: Abdurrahman Dilmac
License: MIT License
Project-URL: Homepage, https://github.com/cerob/google-cloud-functions-tools
Project-URL: Bug Tracker, https://github.com/cerob/google-cloud-functions-tools/issues
Classifier: Programming Language :: Python :: 3
Classifier: License :: OSI Approved :: MIT License
Classifier: Operating System :: OS Independent
Classifier: Intended Audience :: Developers
Requires-Python: >=3.7
License-File: LICENCE
Requires-Dist: firebase-admin
Requires-Dist: flask
